site2md/__init__.py
site2md/api.py
site2md/cache.py
site2md/config.py
site2md/converter.py
site2md/limiting.py
site2md/logging.py
site2md/types.py
site2md-0.1.3.dist-info/METADATA
site2md-0.1.3.dist-info/WHEEL
site2md-0.1.3.dist-info/licenses/LICENSE
site2md-0.1.3.dist-info/RECORD
