Metadata-Version: 2.4
Name: site2md
Version: 0.1.3
Summary: Host an API to convert websites to markdown with optional features
Project-URL: Homepage, https://github.com/davlgd/site2md
Project-URL: Issues, https://github.com/davlgd/site2md/issues
Author-email: David Legrand <1110600+davlgd@users.noreply.github.com>
License: MIT License
License-File: LICENSE
Classifier: Framework :: FastAPI
Classifier: License :: OSI Approved :: MIT License
Classifier: Natural Language :: English
Classifier: Operating System :: OS Independent
Classifier: Programming Language :: Python :: 3
Classifier: Topic :: Text Processing :: Markup :: Markdown
Requires-Python: >=3.9
Requires-Dist: aiofiles>=24.1
Requires-Dist: fastapi>=0.115
Requires-Dist: pydantic>=2.10
Requires-Dist: python-multipart>=0.0.20
Requires-Dist: redis>=5.2
Requires-Dist: requests>=2.32
Requires-Dist: trafilatura>=2.0
Requires-Dist: uvicorn>=0.34
Provides-Extra: dev
Requires-Dist: httpx>=0.28.0; extra == 'dev'
Requires-Dist: pytest-asyncio>=0.25.0; extra == 'dev'
Requires-Dist: pytest-cov>=6.0.0; extra == 'dev'
Requires-Dist: pytest>=8.3.0; extra == 'dev'
